wagtail_pg_search_backend-1.3.2.dist-info/DESCRIPTION.rst
wagtail_pg_search_backend-1.3.2.dist-info/METADATA
wagtail_pg_search_backend-1.3.2.dist-info/RECORD
wagtail_pg_search_backend-1.3.2.dist-info/WHEEL
wagtail_pg_search_backend-1.3.2.dist-info/metadata.json
wagtail_pg_search_backend-1.3.2.dist-info/top_level.txt
wagtail_pgsearchbackend/__init__.py
wagtail_pgsearchbackend/apps.py
wagtail_pgsearchbackend/backend.py
wagtail_pgsearchbackend/models.py
wagtail_pgsearchbackend/utils.py
wagtail_pgsearchbackend/migrations/0001_initial.py
wagtail_pgsearchbackend/migrations/0002_add_gin_index.py
wagtail_pgsearchbackend/migrations/__init__.py
