Metadata-Version: 2.0
Name: wagtail-pg-search-backend
Version: 1.3.2
Summary: PostgreSQL full text search backend for Wagtail CMS
Home-page: https://github.com/leukeleu/wagtail-pg-search-backend
Author: Bertrand Bordage
Author-email: bordage.bertrand@gmail.com
License: MIT
Keywords: wagtail,postgres,fulltext,search
Platform: UNKNOWN
Classifier: Operating System :: OS Independent
Classifier: Programming Language :: Python
Classifier: Programming Language :: Python :: 2.7
Classifier: Programming Language :: Python :: 3.4
Classifier: Programming Language :: Python :: 3.5
Classifier: License :: OSI Approved :: MIT License
Requires-Dist: Django (>=1.10)
Requires-Dist: psycopg2
Requires-Dist: six
Requires-Dist: wagtail
